cbrython_execution/__init__.py
cbrython_execution/execution.py
cbrython_execution-0.1.2.dist-info/METADATA
cbrython_execution-0.1.2.dist-info/WHEEL
cbrython_execution-0.1.2.dist-info/RECORD
